faker_web3/__init__.py
faker_web3/web3.py
faker_web3-1.0.0.dist-info/WHEEL
faker_web3-1.0.0.dist-info/LICENSE
faker_web3-1.0.0.dist-info/METADATA
faker_web3-1.0.0.dist-info/RECORD
