Metadata-Version: 2.1
Name: faker-web3
Version: 1.0.0
Summary: Web3-related fake data provider for Python Faker
Author: Rares Stanciu
Author-email: rcstanciu@protonmail.com
Requires-Python: >=3.8,<4.0
Classifier: Programming Language :: Python :: 3
Classifier: Programming Language :: Python :: 3.8
Classifier: Programming Language :: Python :: 3.9
Classifier: Programming Language :: Python :: 3.10
Classifier: Programming Language :: Python :: 3.11
Requires-Dist: faker (>=16.4.0,<17.0.0)
Requires-Dist: web3 (>=5.31.3,<6.0.0)
